{
  "kind": "spec_vs_diff_report",
  "version": "1.0",
  "generatedAt": "2026-02-19T05:09:14.397Z",
  "summary": "The diff fully implements REQ-12. A 'Contact Us' button with mailto:viitjeetec@gmail.com was added to both the header navigation and footer of the landing page. The button uses the Mail icon from lucide-react, includes accessible label text 'Contact Us', and follows the existing UI patterns with Button component styling consistent with the warm orange theme.",
  "missing_requirements": [],
  "hallucinated_features": [],
  "confidence": 0.95,
  "changed_files": [
    "frontend-file-summaries.txt",
    "frontend/src/App.tsx",
    "project_state.json"
  ]
}